{
  "url": "https://starwars.fandom.com/wiki/Shooting_Star_(EF76_Nebulon-B_escort_frigate)",
  "title": "Shooting Star (EF76 Nebulon-B escort frigate)",
  "pageid": 110807,
  "content": "{{Top|leg|italics=1}}\n{{Otheruses|Shooting Star}}\n[[File:ShootingstarJK.jpg|thumb|right|170px|''Shooting Star'']]\n'''''Shooting Star''''' was an [[EF76 Nebulon-B escort frigate/Legends|EF76 Nebulon-B escort frigate]] that served with the [[Alliance to Restore the Republic/Legends|Alliance to Restore the Republic]] during the [[Galactic Civil War/Legends|Galactic Civil War]].\n\n==Sources==\n*<!-- 2001-10-10 -->{{JKTCG|set=Masters of the Force|cardname=Shooting Star|link=http://www.decipher.com/jediknights/cardlists/mastersoftheforce/large/88shootingstar.html}}\n\n[[Category:EF76 Nebulon-B escort frigates]]\n[[Category:Starships of the Alliance to Restore the Republic]]",
  "length": 671,
  "lastmod": "2026-02-24T23:01:07Z",
  "priority": 1.0
}