{
  "url": "https://starwars.fandom.com/wiki/Quammo",
  "title": "Quammo",
  "pageid": 115028,
  "content": "{{Top|leg}}\n{{Character\n|type=Criminal\n|image=\n|name=Quammo\n|homeworld=\n|birth=\n|death=\n|species=[[Sludir]]\n|gender=[[Gender/Legends|Male]]\n|pronouns=new\n|height=\n|mass=\n|hair=\n|feathers=\n|eyes=\n|skin=\n|cyber=\n|families=new\n|parents=new\n|partners=new\n|siblings=new\n|children=new\n|affiliation=[[Guttu]]\n|masters=\n|apprentices=\n}}\n'''Quammo''' was a [[Sludir]] [[Majordomo/Legends|majordomo]] working for [[gangster]] [[Guttu]] the [[Hutt/Legends|Hutt]] around [[0 ABY/Legends|0 ABY]]. At that time, Guttu said he had not moved by his own means since at least [[150 BBY/Legends|150 BBY]], which explains some of Quammo's responsibilities.\n\n{{Char-stub}}\n\n==Appearances==\n*{{JournalCite|15|The Great Herdship Heist}} {{1st}}\n\n[[Category:Majordomos]]\n[[Category:Males]]\n[[Category:Servants]]\n[[Category:Sludir]]",
  "length": 807,
  "lastmod": "2026-02-09T21:04:39Z",
  "priority": 1.0
}