{
  "url": "https://starwars.fandom.com/wiki/5000x2_%22Tru-Lok%22_laser_cannon",
  "title": "5000x2 \"Tru-Lok\" laser cannon",
  "pageid": 118420,
  "content": "{{Top|leg}}\n{{Otheruses|Lok}}\n{{Weapon\n|image=\n|name=5000x2 \"Tru-Lok\" laser cannon\n|manufacturer=[[Senko Systems]]<ref name=\"HESB\">''[[Heir to the Empire Sourcebook]]''</ref>\n|model=\n|type=[[Laser cannon/Legends|Laser cannon]]<ref name=\"HESB\" />\n|culture=\n|creators=\n|created=\n|destroyed=\n|discovered=\n|owners=\n|locations=\n|cost=\n|value=\n|shape=\n|size=\n|material=\n|length=\n|width=\n|diam=\n|height=\n|weight=\n|protection=\n|crew=\n|capacity=\n|range=\n|inscription=\n|markings=\n|purpose=\n|heritage=\n|affiliation=\n}}\nThe '''5000x2 \"Tru-Lok\" laser cannon''' was a [[Laser cannon/Legends|laser cannon]] produced by [[Senko Systems]] and found widespread use on the [[GAT-12 Skipray Blastboat|Skipray Blastboat]].\n\n{{Weapon-stub}}\n\n==Sources==\n*<!-- 1992-07-XX -->''[[Heir to the Empire Sourcebook]]''\n*<!-- 1996-04-15 -->''[[The Thrawn Trilogy Sourcebook]]''\n*<!-- 2011-09-13 -->{{DB|starship|skipray|Skipray blastboat}}\n\n==Notes and references==\n{{Reflist}}\n\n[[Category:Senko systems products]]\n[[Category:Starship-mounted laser cannons]]",
  "length": 1028,
  "lastmod": "2026-02-25T19:46:08Z",
  "priority": 1.0
}