{
  "url": "https://starwars.fandom.com/wiki/George_Buza",
  "title": "George Buza",
  "pageid": 118574,
  "content": "{{Top|rwp}}\n{{Person\n|image=[[File:GeorgeBuza.jpg]]\n|name=George Buza\n|birth=[[January 7]], [[1940s#1949|1949]]\n|death=\n|listedpronouns=<!--Only include pronouns if they have been explicitly specified by the individual to which this article pertains.-->\n|nationality=[[Wikipedia:Canada|Canadian]]\n|occupation=Actor, voice actor\n|companies=\n|website=\n}}\n'''George Buza''' (born [[January 7]], [[1940s#1949|1949]]) is an actor whose first role was playing Gregg in one episode of ''Kung Fu''. He later appeared on other live-action films and series like ''Highpoint'', ''Seeing Things'' and ''The Amateur''. Meanwhile he started voicing his first character, [[Chief/Legends|Chief]] [[Chirpa/Legends|Chirpa]], in the first [[Ewoks (television series)|''Ewoks'']] season. A decade later he was a frequent guest star on Fox Kids' ''X-Men'' and appeared on four episodes of ''Mythic Warriors''. His other appearances in cartoon animation were ''Spider-Man'' and ''Beyblade''.\n\nBorn in Cleveland, Ohio, Buza grew up in Canada. After his grandfather took him to the movies, he decided when still a boy that he wanted to be an actor. In 1998 he became a Canadian citizen.\n\n==Actor filmography==\n*[[Wikipedia:Mutant X (TV series)|''Mutant X'']] ... Lexa's Dominion Contact\n*[[Wikipedia:X-Men (film)|''X-Men'']] ... Trucker\n*[[Wikipedia:Friday the 13th (film)|''Friday the 13th'']] ... Biker #2\n*[[Wikipedia:The Twilight Zone|''The Twilight Zone'']] ([[Wikipedia:Crazy as a Soup Sandwich|''Crazy as a Soup Sandwich'']]) ... Gus\n\n==Sources==\n*{{GalaxyCite|1|Boba Fett: Mystery Man in Not-So-Shining Armor}}\n\n==External links==\n*{{WP|George Buza}}\n*{{IMDb|name/nm0125579}}\n*{{WebCite|url=http://radiofreesacramento.com/?p=323|text=From JEDI to Television: The Saga of the EWOKS and DROIDS Adventure Hour – Part II|author=Post, Dennis|date=2015-09-07|archiveurl=https://archive.is/cCLwP}}\n\n{{Interlang\n|es=George Buza\n}}\n\n[[Category:Star Wars: Ewoks voice actors]]",
  "length": 1950,
  "lastmod": "2026-02-25T19:46:08Z",
  "priority": 1.0
}