{
  "url": "https://starwars.fandom.com/wiki/Calamari_Sea",
  "title": "Calamari Sea",
  "pageid": 119656,
  "content": "{{Top|leg}}\nThe '''Calamari Sea''', also known as the '''Mon Calamari Sea''', was the [[Planet/Legends|planet]]-spanning [[Ocean/Legends|ocean]] located on [[Dac/Legends|Mon Calamari]]. During the [[Battle of Calamari]], [[World Devastator]]s dropped into this sea.\n\n{{Nature-stub}}\n\n==Appearances==\n*[[Dark Empire 2|''Dark Empire'' 2]] {{1st}}\n*[[Dark Empire 4|''Dark Empire'' 4]]\n\n==Sources==\n*<!-- 1991-12-12 -->[[Dark Empire endnotes|''Dark Empire'' endnotes]]\n*<!-- 2008-12-09 -->''[[The Complete Star Wars Encyclopedia]]'' {{ID|Mon Calamari Sea}}\n\n{{Interlang\n|tr=Kalamari Denizi\n}}\n\n[[Category:Mon Cala locations]]\n[[Category:Seas and oceans]]",
  "length": 650,
  "lastmod": "2025-11-16T04:33:18Z",
  "priority": 1.0
}