{
  "url": "https://starwars.fandom.com/wiki/Automated_conveyor",
  "title": "Automated conveyor",
  "pageid": 120055,
  "content": "{{Top|leg}}\n[[File:Automatedconveyor.jpg|thumb|250px]]\n\n'''Automated conveyors''' moved cargo drums within the holds of [[Rebel ship of the line|Rebel ships of the line]]. [[13-K]] took over such a conveyor, making it drop drums in an attempt to kill [[Luke Skywalker/Legends|Luke Skywalker]].\n\n{{Tech-stub}}\n\n==Appearances==\n*[[Star Wars (1977) 45|''Star Wars'' (1977) 45]] {{Reprint|Star Wars (1977) 45}} {{1st}}\n\n[[Category:Transportation technology]]",
  "length": 454,
  "lastmod": "2026-02-09T21:01:54Z",
  "priority": 1.0
}