{
  "url": "https://starwars.fandom.com/wiki/Larmalstone",
  "title": "Larmalstone",
  "pageid": 127957,
  "content": "{{Top|leg}}\n'''Larmalstone''' or '''larmal''' was a type of expensive rock found only in the [[Roche asteroid field]]. [[Milk/Legends|Milky]] in [[Color/Legends|color]], it was used as a floor covering, as well as to produce statues and other furniture.\n\n[[Han Solo/Legends|Han Solo]] and [[Leia Organa Solo/Legends|Leia Organa Solo]] had a larmalstone floor in the cul-de-sac leading to their [[Eastport/Legends|Eastport]] [[Solo apartment|apartment]] on [[Coruscant/Legends|Coruscant]].\n\n[[Admiral/Legends|Admiral]] [[Nek Bwua'tu]] had a larmalstone bust of Admiral [[Gial Ackbar/Legends|Ackbar]] aboard the [[Galactic Federation of Free Alliances|Galactic Alliance]] ship [[Admiral Ackbar (Victory-class)|''Admiral Ackbar'']].\n\nA priceless larmal-topped end table was present in the [[Queen Mother's Special Salon]] on [[Hapes/Legends|Hapes]]. In [[40 ABY/Legends|40 ABY]], Leia Organa Solo had to restrain Han Solo from throwing it at a very annoying [[pendulum clock]].\n\nThe planet Coruscant's [[New Jedi Temple]] contained a meeting chamber for the [[Jedi High Council/Legends|Jedi Council]] that bore larmalstone flooring.<ref name=\"Vortex\">''[[Fate of the Jedi: Vortex]]''</ref>\n\n==Appearances==\n*''[[A Forest Apart]]''\n*''[[The New Jedi Order: Star by Star]]'' {{1st}}\n*''[[Dark Nest II: The Unseen Queen]]'' {{Mo}}\n*''[[Legacy of the Force: Tempest]]''\n*''[[Legacy of the Force: Inferno]]''\n*''[[Fate of the Jedi: Abyss]]'' {{Ab|Fate of the Jedi: Abyss (audiobook)}}\n*''[[Fate of the Jedi: Vortex]]'' {{Ab|Fate of the Jedi: Vortex (audiobook)}}\n*''[[Fate of the Jedi: Apocalypse]]'' {{Ab|Fate of the Jedi: Apocalypse (audiobook)}}\n*[[Crucible (novel)|''Crucible'']] {{Ab|Crucible (audiobook)}}\n\n==Notes and references==\n{{Reflist}}\n\n{{Interlang\n|de=Larmalstein\n}}\n\n[[Category:Rocks]]",
  "length": 1793,
  "lastmod": "2025-11-16T04:33:18Z",
  "priority": 1.0
}