{
  "url": "https://starwars.fandom.com/wiki/Stericlean",
  "title": "Stericlean",
  "pageid": 140938,
  "content": "{{Top|leg}}\n'''Stericlean''' was used to wash skin.\n\n{{Substance-stub}}\n\n==Appearances==\n*''[[The New Jedi Order: Star by Star]]'' {{1stm}}\n*''[[Dark Nest I: The Joiner King]]'' {{1st}}\n*''[[Dark Nest III: The Swarm War]]''\n*''[[Legacy of the Force: Revelation]]''\n*''[[Legacy of the Force: Invincible]]''\n\n[[Category:Substances]]",
  "length": 330,
  "lastmod": "2025-11-16T04:33:18Z",
  "priority": 1.0
}