{
  "url": "https://starwars.fandom.com/wiki/Ti_(disambiguation)",
  "title": "Ti (disambiguation)",
  "pageid": 147090,
  "content": "Five individuals carry the last name '''Ti''':\n*'''[[Sanola Ti]]''', a [[Human/Legends|Human]] Jedi.\n*'''[[Shaak Ti/Legends|Shaak Ti]]''', a [[Togruta/Legends|Togruta]] [[Jedi/Legends|Jedi]].\n*'''[[Kirana Ti]]''', a [[Human/Legends|Human]] Jedi.\n*'''[[Fionah Ti]]''', a [[Human/Legends|Human]] [[Shaper caste|Shaper]].\n*'''[[Vaash Ti]]''', a [[Togruta/Legends|Togruta]] [[Jedi Initiate/Legends|Jedi Initiate]] related to the previously mentioned Shaak Ti.\n{{Disambig}}\n\n{{Interlang\n|de=Ti\n}}",
  "length": 491,
  "lastmod": "2025-08-08T19:54:21Z",
  "priority": 1.0
}