{
  "url": "https://starwars.fandom.com/wiki/Silphum",
  "title": "Silphum",
  "pageid": 152758,
  "content": "{{Top|leg}}\nA '''silphum''' was a part of the [[Acklay/Legends|Acklay]] creature, with which it detected electrical current.\n\n==Sources==\n*<!-- 2002-04-23 -->''[[Star Wars: Attack of the Clones: The Visual Dictionary]]'' {{1stm}}\n*<!-- 2006-09-25 -->''[[Star Wars: The Complete Visual Dictionary]]''\n*<!-- 2006-10-31 -->''[[The New Essential Guide to Alien Species]]''\n\n{{Interlang\n|nl=Silphum\n}}\n\n[[Category:Anatomy]]",
  "length": 418,
  "lastmod": "2025-11-16T04:33:19Z",
  "priority": 1.0
}