{
  "url": "https://starwars.fandom.com/wiki/Dakuyl",
  "title": "Dakuyl",
  "pageid": 16564,
  "content": "{{Top|leg}}\n{{CelestialBody\n|image=\n|name=Dakuyl\n|region=[[Outer Rim Territories/Legends|Outer Rim Territories]]<ref name=\"Atlas\">''[[The Essential Atlas]]''</ref>\n|sector=[[Stensen sector/Legends|Stensen sector]]<ref name=\"Atlas\" />\n|system=[[Verkuyl system/Legends|Verkuyl system]]<ref name=\"Atlas\" />\n|coordinates=H-17<ref name=\"Atlas\" />\n|xyz=\n|distance=\n|suns=\n|orbited=\n|position=\n|moons=\n|routes=\n|lengthday=\n|lengthyear=\n|class=\n|diameter=\n|atmosphere=\n|climate=\n|gravity=\n|terrain=*Fields\n*Rainforests\n|water=\n|interest=\n|flora=\n|fauna=\n|otherlife=\n|species=\n|otherspecies=\n|socialgroup=\n|language=\n|government=\n|population=\n|demonym=\n|cities=\n|imports=\n|exports=\n|affiliation=[[Galactic Empire/Legends|Galactic Empire]]\n}}\n'''Dakuyl''' was a [[Planet/Legends|planet]] located within the [[Verkuyl system/Legends|Verkuyl system]] of the [[Outer Rim Territories/Legends|Outer Rim Territories]] where [[Alazhi/Legends|alazhi]] was grown. It was in the same [[Star system/Legends|system]] as [[Verkuyl]] and a secondary [[Bacta/Legends|bacta]] production was begun on the planet, but halted after the [[Battle of Endor/Legends|Battle of Endor]].\n\n==Appearances==\n*{{JournalCite|13|Conflict of Interest}} {{1stm}}\n\n==Sources==\n*<!-- 2009-08-18 -->''[[The Essential Atlas]]''\n\n==Notes and references==\n{{Reflist}}\n\n[[Category:Galactic Empire planets]]\n[[Category:Planets in the Outer Rim Territories]]\n[[Category:Stensen sector locations]]\n[[Category:Terrestrial planets]]",
  "length": 1476,
  "lastmod": "2026-02-22T17:44:08Z",
  "priority": 1.0
}