{
  "url": "https://starwars.fandom.com/wiki/Distortion_field_emitter",
  "title": "Distortion field emitter",
  "pageid": 171081,
  "content": "{{Top|leg}}\n\n{{Tech-stub}}\n\nA '''distortion field emitter''' was a device used to create a [[Distortion field/Legends|distortion field]], enabling those within the field to talk privately without concern that their conversation could be electronically bugged. The emitter could be positioned discretely as its appearance was like that of a rolled up pellet of [[Flimsiplast/Legends|flimsiplast]].\n\n[[Kal Skirata]] used a distortion field emitter when discussing his anti-terror operation with [[Jaller Obrim]] at the [[Coruscant Security Force/Legends|Coruscant Security Force]] [[Coruscant Security Force Staff and Social Club|Staff and social club]].\n\n==Appearances==\n*''[[Republic Commando: Triple Zero]]'' {{1st}}\n\n[[Category:Countermeasures]]",
  "length": 747,
  "lastmod": "2025-11-16T04:33:20Z",
  "priority": 1.0
}