{
  "url": "https://starwars.fandom.com/wiki/Ozlo",
  "title": "Ozlo",
  "pageid": 171209,
  "content": "{{Top|leg}}\n{{Character\n|type=Jedi\n|image=\n|name=Ozlo\n|homeworld=[[Dac/Legends|Mon Calamari]]\n|birth=\n|death=[[40 ABY/Legends|40 ABY]]\n|species=[[Mon Calamari/Legends|Mon Calamari]]\n|gender=Male\n|pronouns=new\n|height=\n|mass=\n|hair=\n|feathers=\n|eyes=\n|skin=\n|cyber=\n|families=new\n|parents=new\n|partners=new\n|siblings=new\n|children=new\n|affiliation=*[[New Jedi Order]]\n*[[Galactic Federation of Free Alliances|Galactic Alliance]]\n|masters=\n|apprentices=\n}}\n'''Ozlo''' was a [[Mon Calamari/Legends|Mon Calamari]] [[Jedi Knight/Legends|Jedi Knight]]. In [[40 ABY/Legends|40 ABY]], while still young, he was among those [[Jedi/Legends|Jedi]] at the [[Jedi Academy (Ossus)|Ossus Academy]] when the [[Galactic Alliance Guard]] attempted to \"secure\" it, holding the students hostage. Ozlo, unarmed, was able to resist a coma-gas attack on the part of GAG troopers, but when GAG [[Major/Legends|major]] [[Salle Serpa]] began torturing [[Jedi Master/Legends|Jedi Master]] [[Tionne Solusar]] to provoke the Jedi into attack, Ozlo stormed out from hiding to aid her, and was cut down by GAG snipers with multiple shots to the head.\n\n==Appearances==\n*''[[Legacy of the Force: Inferno]]'' {{1st}}\n\n==Sources==\n*<!-- 2008-12-09 -->''[[The Complete Star Wars Encyclopedia]]''\n\n{{Interlang\n|de=Ozlo\n|es=Ozlo\n|pl=Ozlo\n}}\n\n[[Category:Jedi Knights of the New Jedi Order]]\n[[Category:Males]]\n[[Category:Mon Calamari]]",
  "length": 1396,
  "lastmod": "2025-11-16T04:33:20Z",
  "priority": 1.0
}