{
  "url": "https://starwars.fandom.com/wiki/Oseon_sun",
  "title": "Oseon sun",
  "pageid": 17181,
  "content": "{{Top|leg}}\n{{Otheruses|Oseon}}\n{{Star\n|image=\n|name=Oseon sun\n|region=[[Outer Rim Territories/Legends|Outer Rim Territories]]\n|sector=[[Centrality/Legends|Centrality]]\n|system=[[Oseon system/Legends|Oseon system]]\n|coordinates=T-8\n|xyz=\n|routes=\n|distance=\n|orbits=[[Oseon VII]]\n|stations=\n|asteroids=[[Oseon asteroid belt]]s\n*[[Oseon 2795]]\n*[[Oseon 5631]]\n*[[Oseon 5792]]\n*[[Oseon 6845]]\n*[[Oseon 8920]]\n|other=\n|class=\n|diameter=\n}}\nThe '''Oseon sun''' was the primary [[Star/Legends|star]] in the [[Oseon system/Legends|Oseon system]]. Every [[Standard year/Legends|standard year]], it released the [[Flamewind of Oseon/Legends|Flamewind]] that was a major tourist attraction in the [[The galaxy/Legends|galaxy]]. [[Wiorkettle]] and [[Treva Horme]], of [[Planet Dreams, Incorporated|Planet Dreams, Inc]] had a chain in the Oseon.\n\n{{Star-stub}}\n\n==Appearances==\n*''[[Lando Calrissian and the Mindharp of Sharu]]'' {{1st}}\n*''[[Lando Calrissian and the Flamewind of Oseon]]''\n*[[Millennium Falcon (novel)|''Millennium Falcon'']] {{Ab|Millennium Falcon (audiobook)}}\n\n==Sources==\n*<!-- 1989-XX-XX -->''[[Galaxy Guide 3: The Empire Strikes Back]]''\n*<!-- 1994-09-XX -->{{InsiderCite|23|Star Wars Publications Timeline|''Star Wars'' Publications Timeline}}\n*<!-- 2009-08-18 -->''[[The Essential Atlas]]''\n*<!-- 2009-12-08 -->{{Hyperspace|url=fans/hyperspace/source/ximweek02/index.html|text=Xim Week: ''The Despotica'' (Part I)|int=Xim Week: The Despotica}}\n*<!-- 2012-10-02 -->''[[The Essential Reader's Companion]]''\n*<!-- 2013-07-05 -->[[Star Wars: Edge of the Empire Core Rulebook|''Star Wars: Edge of the Empire'' Core Rulebook]]\n\n{{Interlang\n|es=Oseon/Leyendas\n}}\n\n[[Category:Oseon system locations]]\n[[Category:Stars in the Outer Rim Territories]]\n[[Category:Stars in the Slice]]",
  "length": 1787,
  "lastmod": "2026-02-25T19:46:07Z",
  "priority": 1.0
}