{
  "url": "https://starwars.fandom.com/wiki/Panto",
  "title": "Panto",
  "pageid": 17232,
  "content": "{{Top|leg}}\n{{Star\n|image=\n|name=Panto\n|region=*[[Core Worlds/Legends|Core Worlds]]<ref name=\"EAOC\">{{SW|url=news/star-wars-the-essential-atlas-online-companion|text=''Star Wars: The Essential Atlas'' Online Companion|int=Star Wars: The Essential Atlas Online Companion}}</ref>\n*[[Northern Dependencies/Legends|Northern Dependencies]]<ref name=\"Region\">''[[The Essential Atlas]]'' &mdash; [[:File:MiscellaneousRegions.jpg|Client States and Miscellaneous Regions map]]</ref>\n|sector=[[Dolomar sector/Legends|Dolomar sector]]\n|system=[[Panto system]]\n|coordinates=K-9\n|xyz=\n|routes=[[Namadii Corridor/Legends|Namadii Corridor]]\n|distance=\n|orbits=#[[Pantolomin/Legends|Pantolomin]]\n|stations=[[Jervo's World]]\n|asteroids=\n|other=\n|class=\n|diameter=\n}}\n'''Panto''' was the [[Star/Legends|star]] of the [[Panto system]], and was orbited by three [[Planet/Legends|planets]], with the closest being [[Pantolomin/Legends|Pantolomin]].\n\n==Sources==\n*<!-- 1993-04-XX -->''[[Dark Force Rising Sourcebook]]'' {{1stm}}\n*<!-- 1994-03-XX -->''[[A Guide to the Star Wars Universe, Second Edition, Revised and Expanded]]'' {{Imo}}\n*<!-- 1996-04-15 -->''[[The Thrawn Trilogy Sourcebook]]''\n*<!-- 2004-05-12 -->{{FactFile|124|PAN 1-2|Pantolomin}}\n\n==Notes and references==\n{{Reflist}}\n\n{{Interlang\n|es=Panto\n}}\n\n[[Category:Panto system locations]]\n[[Category:Stars in the Core Worlds]]\n[[Category:Stars in the Northern Dependencies]]",
  "length": 1415,
  "lastmod": "2026-03-04T22:15:21Z",
  "priority": 1.0
}