{
  "url": "https://starwars.fandom.com/wiki/Team_Eight",
  "title": "Team Eight",
  "pageid": 178927,
  "content": "{{Top|leg}}\n'''Team Eight''' was a team of [[Noghri Death Commando]]s under the command of [[Mitth'raw'nuruodo/Legends|Thrawn]]. They were sent to [[Bimmisaari/Legends|Bimmisaari]] to capture [[Luke Skywalker/Legends|Luke Skywalker]] and [[Leia Organa Solo/Legends|Leia Organa Solo]]. All were killed except for their handler.\n\n==Appearances==\n*''[[Heir to the Empire]]'' {{Ab|Heir to the Empire (unabridged audiobook)}}\n\n{{Interlang\n|de=Team Acht\n}}\n\n[[Category:Imperial military units]]",
  "length": 488,
  "lastmod": "2025-11-16T04:33:20Z",
  "priority": 1.0
}