{
  "url": "https://starwars.fandom.com/wiki/Proton_Overload",
  "title": "Proton Overload",
  "pageid": 20241,
  "content": "{{Top|leg}}\n'''[[Proton Overload]]''' was a [[Band/Legends|band]] that occasionally played at [[Bantha Traxx]] on [[Lianna/Legends|Lianna]]. Their signature song was \"[[Shoot First]].\"<ref name=\"Wretched\">''[[Wretched Hives of Scum & Villainy]]''</ref>\n\n==Sources==\n*<!-- 1997-05-12 -->''[[Wretched Hives of Scum & Villainy]]''\n\n==Notes and references==\n{{Reflist}}\n\n{{Interlang\n|de=Proton Overload#legends\n}}\n\n[[Category:Bands]]",
  "length": 429,
  "lastmod": "2025-11-16T04:33:12Z",
  "priority": 1.0
}