{
  "url": "https://starwars.fandom.com/wiki/Cesa",
  "title": "Cesa",
  "pageid": 22310,
  "content": "{{Top|leg}}\n{{Game\n|image=[[File:Gorothcesagame.jpg]]\n|name=Cesa\n|type=\n|players=Two\n|ages=\n|createdby=\n|first=\n|locations=[[Goroth Prime/Legends|Goroth Prime]]\n|affiliation=\n}}\n'''Cesa''' was a game popular among the [[Gorothite/Legends|Gorothite]] species. Cesa was played by two people and used an ornate checkerboard formed from ten squares on each side. The rules on how to move the pieces across the board were very simple. Among Gorothites the game ranged from being a hobby to an obsession.\n\n==Sources==\n*<!-- 1995-01-XX -->''[[Goroth: Slave of the Empire]]''\n\n[[Category:Board games]]",
  "length": 593,
  "lastmod": "2025-11-16T04:33:12Z",
  "priority": 1.0
}