{
  "url": "https://starwars.fandom.com/wiki/Onslaught_(Star_Destroyer)",
  "title": "Onslaught (Star Destroyer)",
  "pageid": 25832,
  "content": "{{Top|leg|italics=1}}\n{{Youmay|the ship|''[[The New Jedi Order: Dark Tide I: Onslaught]]''}}\n{{IndividualShip\n|image=\n|name=''Onslaught''\n|designer=\n|manufacturer=\n|line=\n|model=\n|type=[[Star Destroyer/Legends|Star Destroyer]]\n|cost=\n|modifier=\n|sysmods=\n|length=\n|width=\n|height=\n|mass=\n|max accel=\n|mglt=\n|max speed=\n|maneuverability=\n|engine=\n|hyperdrive=\n|hdrange=\n|hdsystem=\n|poweroutput=\n|power=\n|shield gen=\n|hull=\n|sensor=\n|target=\n|navigation=\n|avionics=\n|maincomp=\n|countermeasures=\n|armament=\n|complement=\n|bays=\n|escapepods=\n|crew=\n|skeleton=\n|passengers=\n|capacity=\n|cargohandling=\n|consumables=\n|lifesupport=\n|communications=\n|othersystems=\n|role=\n|commission=\n|destroyed=\n|retired=\n|battles=\n|affiliation=[[Galactic Empire/Legends|Galactic Empire]]\n|navy=\n|fleet=\n|owners=\n|captains=[[Alecs Brellar]]\n|crewmembers=\n|registry=\n|aliases=\n}}\nThe '''''Onslaught''''' was an [[Galactic Empire/Legends|Imperial]] [[Star Destroyer/Legends|Star Destroyer]] of the [[Imperial Navy/Legends|Imperial Navy]].\n\nIn [[0 ABY/Legends|0 ABY]], the ''Onslaught'' was dispatched to [[Bakura/Legends|Bakura]] under [[Captain/Legends|Captain]] [[Alecs Brellar]] to bring the system into the [[Galactic Empire/Legends|Galactic Empire]].\n\n{{Ship-stub}}\n\n==Appearances==\n*{{JournalCite|5|Galaxywide NewsNets}}\n\n==Sources==\n*<!-- 2008-12-09 -->''[[The Complete Star Wars Encyclopedia]]''\n\n[[Category:Star Destroyers]]\n[[Category:Starships of the Galactic Empire]]",
  "length": 1452,
  "lastmod": "2026-02-09T21:04:38Z",
  "priority": 1.0
}