{
  "url": "https://starwars.fandom.com/wiki/New_Architecture",
  "title": "New Architecture",
  "pageid": 27619,
  "content": "{{Top|leg}}\n'''New Architecture''' was an architectural style used in the [[Senate District/Legends|Senate District]] on [[Coruscant/Legends|Coruscant]], where the upper layers were dominated with domes, spires, and blade-thin obelisks.\n\n==Appearances==\n*''[[Labyrinth of Evil]]''\n\n[[Category:Architecture]]",
  "length": 307,
  "lastmod": "2025-11-16T04:33:13Z",
  "priority": 1.0
}