{
  "url": "https://starwars.fandom.com/wiki/Star_Wars:_Ewoks_(1985)",
  "title": "Star Wars: Ewoks (1985)",
  "pageid": 31051,
  "content": "{{Top|rwm|reb|italics=1}}\n{{Otheruses|Ewok}}\n{{ComicSeries\n|image=[[File:MARVELEWOKS1.jpg]]\n|title=''Star Wars: Ewoks''\n|writer=[[David Manak|Dave Manak]]\n|penciller=[[Warren Kremer]]\n|inker=Various\n|letterer=[[Grace Kremer]]\n|colorist=Various\n|cover artist=Warren Kremer\n|editor=*[[Sid Jacobson]]\n*[[Tom DeFalco]]\n|publisher=[[Marvel Comics]]/[[Star Comics]]\n|start date=[[January 29]], [[1985]]<ref name=\"Marvel Age 25\">{{BookCite|title=[[Marvel Age]]|number=Vol. 1 No. 25|publisher=[[Marvel Comics]] Group|date=[[April]] [[1985]]}}</ref>\n|end date=[[March 31]], [[1987]]<ref name=\"Marvel Age 51\">''[[Marvel Age]]'' 51</ref>\n|schedule=Bimonthly\n|format=\n|issues=14\n|timeline=\n|series=\n|preceded by=\n|followed by=\n}}\n{{Quote|Now, at long last, the fierce fuzzy fighters from the smash movie 'The Return of the Jedi,' '''the Ewoks''', have their very own comic series!|''Marvel Age'' 25|<ref name=\"Marvel Age 25\" />}}\n'''''Star Wars: Ewoks''''' was a fourteen-issue series of comics published by [[Star Comics]], an imprint of [[Marvel Comics]], from [[1985]] to [[1987]]. The series was a tie-in to [[Ewoks (television series)|the animated series]] and was aimed at a young audience. The series' first four issues were released before the television show premiered.\n\nA [[Ewoks (1985) 15|fifteenth issue]] of the series was solicited but never published.<ref name=\"Marvel Age\">''Marvel Age 53''</ref>  [[Ewoks Annual|An annual]] published in the UK in [[1988]] features stories reprinted from this series plus some original short stories.<ref name=\"Annuals\">{{SW|url=news/star-wars-in-the-uk-star-wars-comic-book-annuals|text=''Star Wars'' in the UK: ''Star Wars'' Comic Book Annuals}}</ref>\n\n{{Comics-stub}}\n\n==Media==\n{{Mediacat|from=1|imagecat=Images from Star Wars: Ewoks (1985)}}\n===Issues===\n*[[Ewoks (1985) 1|''Ewoks'' 1]]\n*[[Ewoks (1985) 2|''Ewoks'' 2]]\n*[[Ewoks (1985) 3|''Ewoks'' 3]]\n*[[Ewoks (1985) 4|''Ewoks'' 4]]\n*[[Ewoks (1985) 5|''Ewoks'' 5]]\n*[[Ewoks (1985) 6|''Ewoks'' 6]]\n*[[Ewoks (1985) 7|''Ewoks'' 7]]\n*[[Ewoks (1985) 8|''Ewoks'' 8]]\n*[[Ewoks (1985) 9|''Ewoks'' 9]]\n*[[Ewoks (1985) 10|''Ewoks'' 10]]\n*[[Ewoks (1985) 11|''Ewoks'' 11]]\n*[[Ewoks (1985) 12|''Ewoks'' 12]]\n*[[Ewoks (1985) 13|''Ewoks'' 13]]\n*[[Ewoks (1985) 14|''Ewoks'' 14]]\n*[[Ewoks (1985) 15|''Ewoks'' 15]] {{C|canceled issue}}\n*''[[Star Wars Annual Featuring Ewoks]]'' (1985)\n*''[[Ewoks Annual]]'' (1988)\n\n===Collected in===\n*<!-- 2012-06-06 -->''[[Star Wars Omnibus: Droids and Ewoks]]''\n*<!-- 2016-06-14 -->''[[Star Wars: Droids & Ewoks Omnibus]]''\n*<!-- 2019-03-06 -->''[[Star Wars: Ewoks — Flight to Danger]]''\n*<!-- 2024-11-12 -->''[[Star Wars Legends Epic Collection: The Original Marvel Years - Droids & Ewoks]]''\n\n==Sources==\n*<!-- 1994-09-XX -->{{InsiderCite|23|Star Wars Publications Timeline|''Star Wars'' Publications Timeline}}\n*<!-- 2013-11-16 -->{{SW|url=news/star-wars-in-the-uk-star-wars-comic-book-annuals|text=''Star Wars'' in the UK: ''Star Wars'' Comic Book Annuals}}\n*<!-- 2024-10-29 -->{{InsiderCite|228|Launchpad}}\n\n==Notes and references==\n{{Reflist}}\n\n==External links==\n*{{Marvel|url=comics/series/20171/star_wars_ewoks_1985_-_1987|text=Star Wars: Ewoks (1985 - 1987)}}\n\n{{EwoksEpisodes}}\n\n{{Interlang\n|es=Ewoks (Marvel)\n|ka=ვარსკვლავური ომები: ევოკები (1985)\n}}\n\n[[Category:Legends ongoing series|Ewoks 1985]]\n[[Category:Marvel Comics ongoing series|Ewoks 1985]]\n\n{{RelatedCategories\n|[[Category:Star Wars: Ewoks (1985) issues]]\n}}",
  "length": 3443,
  "lastmod": "2026-03-04T22:15:21Z",
  "priority": 1.0
}