{
  "url": "https://starwars.fandom.com/wiki/Coruscant_Fashions",
  "title": "Coruscant Fashions",
  "pageid": 31654,
  "content": "{{Top|leg}}\n{{Structure\n|image=\n|name=Coruscant Fashions\n|constructed=\n|destroyed=\n|type=\n|location=[[Cinnagar/Legends|Cinnagar]], [[Empress Teta/Legends|Empress Teta]]<ref name=\"NoP\">''[[Nexus of Power]]''</ref>\n|interest=\n|rebuilt=\n|builder=\n|height=\n|width=\n|affiliation=\n}}\n'''Coruscant Fashions''' was a high-end retailer located within the [[Core District/Legends|Core District]] of the [[City/Legends|city]] of [[Cinnagar/Legends|Cinnagar]]. Like many of the attractions within the Core District, the store's architecture represented a specific [[Planet/Legends|planet]] within the [[Core Worlds/Legends|Core Worlds]] region of [[The galaxy/Legends|the galaxy]]; specifically [[Coruscant/Legends|Coruscant]]. Coruscant Fashions specialized in fashion from the cities of Coruscant and other planets in the region.\n\n{{Loc-stub}}\n\n==Sources==\n*<!-- 2016-03-17 -->''[[Nexus of Power]]''\n\n==Notes and references==\n{{Reflist}}\n\n{{Interlang\n|es=Modas Coruscant\n}}\n\n[[Category:Empress Teta locations]]\n[[Category:Vendors and sellers]]",
  "length": 1033,
  "lastmod": "2025-11-16T04:33:13Z",
  "priority": 1.0
}