{
  "url": "https://starwars.fandom.com/wiki/Yuza_Bre",
  "title": "Yuza Bre",
  "pageid": 43428,
  "content": "{{Top|leg}}\n'''Yuza Bre''' was a high class restaurant built on [[Coruscant/Legends|Coruscant]] after the [[Galactic Federation of Free Alliances|Galactic Alliance]] [[Battle of Yuuzhan'tar|liberated]] the planet from the [[Yuuzhan Vong]]. It was said that reservations took months in advance to get, and it was one of the favorite restaurants of [[Chief of State (Galactic Alliance)|Chief of State]] [[Cal Omas]]. During the [[Swarm War]], [[Aryn Dro Thul]] bought the restaurant after she had been denied repeated requests to see Chief Omas. Madame Thul mused that Omas would suddenly find his request for reservations repeatedly denied. The Yuza Bre was owned by [[Bornaryn Trading]] as of the [[Swarm War]].\n\nYuza Bre specialized in serving [[y'luubi]].\n\n==Appearances==\n*''[[Dark Nest III: The Swarm War]]'' {{1st}}\n\n==Sources==\n*<!-- 2008-12-09 -->''[[The Complete Star Wars Encyclopedia]]''\n\n{{Interlang\n|de=Yuza Bre\n|es=Yuza Bre\n}}\n\n[[Category:Coruscant dining establishments]]",
  "length": 985,
  "lastmod": "2025-11-16T04:33:14Z",
  "priority": 1.0
}