{
  "url": "https://starwars.fandom.com/wiki/Centrally_Controlled_Independent_Replicant",
  "title": "Centrally Controlled Independent Replicant",
  "pageid": 50443,
  "content": "{{Top|leg}}\n'''Centrally Controlled Independent Replicant''' or '''CCIR''', was a type of remote-control technology used by [[Loronar Corporation/Legends|Loronar Corporation]] in [[synthdroid]]s and [[Needle fighter]]s.\n\nCCIR technology allowed multiple automatons to be controlled by large central [[Computer/Legends|computers]] rather than a large number of miniaturized [[Droid/Legends|droid]] brains. The technology relied on near-instantaneous transmission between programmable crystals. The need for only minimal internal computers cut the construction cost for such droids although the cost of programmable crystals proved high until Loronar began enslaving [[Tsil]]s from [[Nam Chorios/Legends|Nam Chorios]] in order to accomplish the instant communication needed.\n\n{{Tech-stub}}\n\n==Appearances==\n*''[[Planet of Twilight]]'' {{1st}}\n*''[[The New Jedi Order: Agents of Chaos I: Hero's Trial]]'' {{Mo}}\n\n==Sources==\n*<!-- 2000-10-XX -->''[[A Guide to the Star Wars Universe, Third Edition, Revised and Expanded]]''\n*<!-- 2001-04-03 -->[[The Essential Guide to Alien Species (real-world book)|''The Essential Guide to Alien Species'']]\n*<!-- 2003-07-23 -->{{FactFile|82|MAN 7-8|Weapons Manufacturers}}\n*<!-- 2008-12-09 -->''[[The Complete Star Wars Encyclopedia]]''\n\n[[Category:Communications]]\n[[Category:Loronar Corporation products]]",
  "length": 1341,
  "lastmod": "2026-02-09T21:04:38Z",
  "priority": 1.0
}