{
  "url": "https://starwars.fandom.com/wiki/Malcraan",
  "title": "Malcraan",
  "pageid": 51747,
  "content": "{{Top|leg}}\n'''Malcraan''' was a [[City/Legends|city]] on the [[Planet/Legends|planet]] [[Molavar/Legends|Molavar]] where [[Darca Nyl]] began his pursuit of [[Lycan]]. [[Magon]] was based there.\n\n{{City-stub}}\n\n==Appearances==\n*{{Tales|issue1=21|issue2=24|Nomad}} {{Mo}}\n\n{{Interlang\n|es=Malcraan\n|fr=Malcraan\n}}\n\n[[Category:Cities]]",
  "length": 333,
  "lastmod": "2025-11-16T04:33:14Z",
  "priority": 1.0
}