{
  "url": "https://starwars.fandom.com/wiki/Coreguard_Security_Services",
  "title": "Coreguard Security Services",
  "pageid": 53544,
  "content": "{{Top|leg}}\n'''Coreguard Security Services''' was a security services company located on the [[Planet/Legends|world]] of [[Corulag/Legends|Corulag]]. They provided security to other corporations on the planet.<ref name=\"SF\">{{JournalCite|12|Small Favors}}</ref>\n\n{{Company-stub}}\n\n==Appearances==\n*{{JournalCite|12|Small Favors}} {{1st}}\n\n==Sources==\n*<!-- 2004-06-10 -->''[[Ultimate Adversaries]]''\n\n==Notes and references==\n{{Reflist}}\n\n[[Category:Security companies]]",
  "length": 470,
  "lastmod": "2026-02-09T21:04:38Z",
  "priority": 1.0
}