{
  "url": "https://starwars.fandom.com/wiki/Attack_on_a_Tatooine_Imperial_base",
  "title": "Attack on a Tatooine Imperial base",
  "pageid": 54482,
  "content": "{{Top|ncl}}\n{{Noncanon|legends=1}}\n{{Battle\n|prev=[[Raid on the Vergesso Asteroids]]\n|conc=\n|next=\n|image=\n|name=Attack on a Tatooine Imperial base\n|conflict=[[Galactic Civil War/Legends|Galactic Civil War]]\n|date=[[3 ABY/Legends|3 ABY]]\n|place=[[Tatooine/Legends|Tatooine]]\n|result=Rebel Alliance victory\n|side1=[[Alliance to Restore the Republic/Legends|Alliance to Restore the Republic]]\n|side2=[[Galactic Empire/Legends|Galactic Empire]]\n|side3=\n|side4=\n|commanders1=*[[Han Solo/Legends|Han Solo]]\n*[[Chewbacca/Legends|Chewbacca]]\n|commanders2=[[Boba Fett/Legends|Boba Fett]]\n|commanders3=\n|commanders4=\n|unit1=\n|unit2=\n|unit3=\n|unit4=\n|forces1=*[[Alliance Special Forces/Legends|Rebel troopers]]\n*[[T2-B Repulsor Tank/Legends|T2-B repulsor tanks]]\n*[[T4-B heavy tank]]s\n*[[Jawa/Legends|Jawa]] and [[Human/Legends|Human]] civilians rebelling\n*[[Mobile Proton Torpedo Launcher-2a|MPTL-2a artillery]]\n*[[BTL Y-wing starfighter/Legends|BTL Y-wing starfighters]]\n*[[GR-75 medium transport/Legends|GR-75 medium transport]]\n|forces2=*[[Stormtrooper/Legends|Stormtroopers]]\n*[[74-Z speeder bike/Legends|74-Z speeder bikes]]\n*[[TIE ap-1|TIE Maulers]]\n*[[All Terrain Scout Transport/Legends|AT-ST walkers]]\n*[[All Terrain Armored Transport/Legends|AT-AT walkers]]\n|forces3=\n|forces4=\n|casual1=*Medium\n|casual2=*Heavy\n|casual3=\n|casual4=\n|civilian=\n}}\nWith the [[Galactic Empire/Legends|Imperial]] outpost in the [[Vergesso Asteroids/Legends|Vergesso Asteroids]] fallen, the '''attack on a Tatooine Imperial base''' started when the Alliance fleet moved from the Vergesso asteroids to [[Tatooine/Legends|Tatooine]].\n\n==The battle==\nAlliance Commandos infiltrated an Imperial base, took down the shields, and allowed bombing runs to take place, but suffered several casualties at the hands of [[Boba Fett/Legends|Boba Fett]], who was hired by the Empire to guard the base at the time. After the shields were brought down, [[BTL Y-wing starfighter/Legends|Y-Wings]] were used to destroy the Imperial base. Then GR-75 transports landed near by and dispatched Rebel soldiers who then moved into the area to clean up any heavy resistance. Boba Fett escaped however. Many stormtroopers were taken captive and their base destroyed.\n\n{{Battle-stub}}\n\n==Appearances==\n*''[[Star Wars: Empire at War]]''\n\n{{Interlang\n|es=Segunda Batalla de Tatooine (Guerra Civil Galáctica)\n|pt=Segunda Batalha de Tatooine (Guerra Civil Galáctica)\n}}\n\n{{DEFAULTSORT:Tatooine Imperial base, attack on a}}\n[[Category:Battles of Tatooine]]\n[[Category:Battles of the Galactic Civil War]]",
  "length": 2549,
  "lastmod": "2026-02-18T19:12:09Z",
  "priority": 1.0
}