{
  "url": "https://starwars.fandom.com/wiki/Ganrite_Yards_of_Elrood,_Inc.",
  "title": "Ganrite Yards of Elrood, Inc.",
  "pageid": 57787,
  "content": "{{Top|leg}}\n'''Ganrite Yards of Elrood, Inc.''' was an [[Elrood/Legends|Elrood]]-based [[Starship/Legends|starship]] manufacturing corporation with offices located in the [[Elrood Bazaar]]. They primarily produced clones of other starshipwright's established designs, including the [[Bratilia light freighter]].\n\n{{Company-stub}}\n\n==Sources==\n*<!-- 1993-09-XX -->''[[Planets of the Galaxy, Volume Three]]''\n*<!-- 1994-11-XX -->''[[The Star Wars Planets Collection]]''\n\n[[Category:Shipwrights]]",
  "length": 493,
  "lastmod": "2025-11-16T04:33:14Z",
  "priority": 1.0
}