{
  "url": "https://starwars.fandom.com/wiki/Morr",
  "title": "Morr",
  "pageid": 61042,
  "content": "{{Top|leg}}\n{{Character\n|type=Bounty hunter\n|image=\n|name=Morr\n|homeworld=\n|birth=\n|death=\n|species=[[Defel/Legends|Defel]]<ref name=\"GG10\">''[[Galaxy Guide 10: Bounty Hunters]]''</ref>\n|gender=[[Gender/Legends|Female]]<ref name=\"GG10\" />\n|pronouns=new\n|height=\n|mass=\n|hair=\n|feathers=\n|eyes=\n|skin=\n|cyber=\n|families=new\n|parents=new\n|partners=new\n|siblings=new\n|children=new\n|affiliation=\n|masters=\n|apprentices=\n}}\n'''Morr''' was a [[Gender/Legends|female]] [[Defel/Legends|Defel]] [[Bounty hunter/Legends|bounty hunter]].\n\n==History==\nMorr, a [[Defel/Legends|Defel]], became a [[Bounty hunter/Legends|bounty hunter]] when a [[Merchant/Legends|trader]] broke [[Gender/Legends|his]] word with several other Defel. Morr hunted the man down and brought him to answer for his betrayal. She found that her natural abilities granted her a great advantage in her new profession, and that she greatly liked hunting.\n\nShe utilized both the fact that most beings believed Defel to be legends and the vast subterranean complexes of many [[Planet/Legends|planets]] in order to take unsuspecting [[Bounty/Legends|bounties]] by surprise. She was fiercely loyal to the few friends and contacts she had established, and was disgusted by those who did not keep their word.\n\n==Sources==\n*<!-- 1994-03-XX -->''[[Galaxy Guide 10: Bounty Hunters]]'' {{1stm}}\n*<!-- 2003-04-XX -->''[[Ultimate Alien Anthology]]''\n\n==Notes and references==\n{{Reflist}}\n\n{{Interlang\n|de=Morr#legends\n}}\n\n[[Category:Bounty hunters]]\n[[Category:Defel]]\n[[Category:Females]]",
  "length": 1534,
  "lastmod": "2025-11-16T04:33:14Z",
  "priority": 1.0
}