{
  "url": "https://starwars.fandom.com/wiki/Plah",
  "title": "Plah",
  "pageid": 61942,
  "content": "{{Top|leg}}\n{{CelestialBody\n|image=[[File:Tibrin_SWCCG.png]]\n|name=Plah (right)\n|region=[[Mid Rim/Legends|Mid Rim]]<ref name=\"Atlas\">''[[The Essential Atlas]]''</ref>\n|sector=[[Hadar sector/Legends|Hadar sector]]<ref name=\"Atlas\" />\n|system=[[Cal system]]<ref name=\"Atlas\" />\n|coordinates=L-18<ref name=\"Atlas\" />\n|xyz=\n|distance=\n|suns=\n|orbited=[[Tibrin/Legends|Tibrin]]\n|position=\n|moons=\n|routes=\n|lengthday=\n|lengthyear=\n|class=\n|diameter=\n|atmosphere=\n|climate=\n|gravity=\n|terrain=\n|water=\n|interest=\n|flora=\n|fauna=\n|otherlife=\n|species=\n|otherspecies=\n|socialgroup=\n|language=\n|government=\n|population=\n|demonym=\n|cities=\n|imports=\n|exports=\n|affiliation=\n}}\n'''Plah''' was a lifeless [[Moon/Legends|moon]] that [[Orbit/Legends|orbited]] the [[Planet/Legends|planet]] [[Tibrin/Legends|Tibrin]].\n\n{{Moon-stub}}\n\n==Appearances==\n*[[Star Wars: Rebellion (video game)|''Star Wars: Rebellion'']] {{Mo}}\n\n==Sources==\n*<!-- 1989-XX-XX -->''[[Galaxy Guide 4: Alien Races]]'' {{1stm}}\n*<!-- 1994-03-XX -->[[Galaxy Guide 4: Alien Races (Second Edition)|''Galaxy Guide 4: Alien Races'', Second Edition]]\n*<!-- 1998-06-30 -->''[[Star Wars Encyclopedia]]''\n*<!-- 2008-12-09 -->''[[The Complete Star Wars Encyclopedia]]''\n\n==Notes and references==\n{{Reflist}}\n\n[[Category:Cal system locations]]\n[[Category:Moons in the Mid Rim]]\n[[Category:Moons in the Western Reaches]]",
  "length": 1364,
  "lastmod": "2026-02-22T17:44:08Z",
  "priority": 1.0
}