{
  "url": "https://starwars.fandom.com/wiki/Nerf_tenderloin",
  "title": "Nerf tenderloin",
  "pageid": 67763,
  "content": "{{Top|leg}}\n{{Food\n|image=\n|name=Nerf tenderloin\n|origin=\n|date=\n|race=\n|creator=\n|found=\n|type=\n|description=\n|animals=[[Nerf/Legends|Nerf]]\n|plants=\n|other=\n|edible=\n|inedible=\n|potable=\n|nutrition=\n|effects=\n|dishes=\n|affiliation=\n}}\n'''Nerf tenderloin''' was a portion of meat that was cut from the middle of a [[Nerf/Legends|nerf]]. It was usually marinated and served as an elegant and expensive [[Foodstuff/Legends|food]] choice.\n\n==Appearances==\n*{{TORweb|url=info/news/blog/20150403|text=\"Regrets\"|int=Regrets}}\n*''[[The Paradise Snare]]'' {{1st}}\n*''[[Rebel Dawn]]''\n\n[[Category:Meat]]\n[[Category:Nerf foodstuff|tenderloin]]",
  "length": 634,
  "lastmod": "2026-02-27T20:34:04Z",
  "priority": 1.0
}