{
  "url": "https://starwars.fandom.com/wiki/Free_People",
  "title": "Free People",
  "pageid": 73756,
  "content": "{{Top|leg}}\nThe '''Free People''' were a group on [[Wayland/Legends|Wayland]] who resisted the invasion of their homeworld by the [[Yuuzhan Vong]]. The Free People was organized of the locals of Wayland including [[Human/Legends|Humans]], [[Myneyrsh]] and the [[Psadan]]s. Their leader was [[Txer]] and aided [[Uldir Lochett]] when he came to Wayland in search of [[Klin-Fa Gi]].\n\n{{Stub}}\n\n==Appearances==\n*\"[[Emissary of the Void]]\" {{Reprint|Emissary of the Void}}\n\n{{Interlang\n|de=Free People\n|es=Gente Libre\n}}\n\n[[Category:Outer Rim Territories organizations]]",
  "length": 565,
  "lastmod": "2026-02-09T21:01:54Z",
  "priority": 1.0
}