{
  "url": "https://starwars.fandom.com/wiki/Battle_of_Bilbringi_(disambiguation)",
  "title": "Battle of Bilbringi (disambiguation)",
  "pageid": 7448,
  "content": "The '''Battle of Bilbringi''' can refer to:\n\n'''[[Galactic Civil War/Legends|Galactic Civil War]]'''\n*A [[Battle of Bilbringi (6 ABY)|battle]] in [[6 ABY/Legends|6 ABY]]\n*A [[Raid on Bilbringi|raid]] in [[9 ABY/Legends|9 ABY]]\n*The [[Battle of Bilbringi (9 ABY)|Battle of Bilbringi]] in 9 ABY\n*A [[Battle of Bilbringi (10 ABY)|battle]] in [[10 ABY/Legends|10 ABY]]\n\n'''[[Yuuzhan Vong War]]'''\n*The [[Battle of Bilbringi (Yuuzhan Vong War)|Battle of Bilbringi]] in [[25 ABY/Legends|25 ABY]]\n*A [[Attack on the Bilbringi system|battle]] in [[27 ABY/Legends|27 ABY]]\n*The [[Second Battle of Bilbringi]] in [[29 ABY/Legends|29 ABY]]\n\n{{Disambig}}\n\n{{Interlang\n|de=Schlacht von Bilbringi#kanon\n}}\n\n[[Category:Battles in the Bilbringi system| ]]",
  "length": 739,
  "lastmod": "2025-08-08T19:54:18Z",
  "priority": 1.0
}