{
  "url": "https://starwars.fandom.com/wiki/Lecepanine",
  "title": "Lecepanine",
  "pageid": 79026,
  "content": "{{Top|leg}}\n{{Image}}\n'''Lecepanine''' was a drug used in hunting darts as a paralytic and soporific. It created total muscle paralysis within three seconds, and unconsciousness within five seconds.\n\n==Appearances==\n*''[[Star Wars Galaxies: The Ruins of Dantooine]]''\n*{{GalaxiesAED}} {{1st}}\n\n[[Category:Sedatives]]",
  "length": 316,
  "lastmod": "2025-11-16T04:33:16Z",
  "priority": 1.0
}