{
  "url": "https://starwars.fandom.com/wiki/Jangelle",
  "title": "Jangelle",
  "pageid": 80827,
  "content": "{{Top|leg}}\n{{CelestialBody\n|image=[[File:Jangelle.jpg]]\n|name=Jangelle\n|region=[[Outer Rim Territories/Legends|Outer Rim Territories]]\n|sector=*[[Kathol sector/Legends|Kathol sector]]\n**[[Kathol Outback/Legends|Kathol Outback]]\n|system=[[Jangelle system/Legends|Jangelle system]]\n|coordinates=M-21\n|xyz=\n|distance=\n|suns=\n|orbited=\n|position=\n|moons=\n|routes=\n|lengthday=\n|lengthyear=\n|class=\n|diameter=\n|atmosphere=\n|climate=[[Temperature/Legends|Temperate]]\n|gravity=\n|terrain=Sandy lowlands\n|water=Many streams, rivers, and deltas\n|interest=\n|flora=\n|fauna=\n|otherlife=\n|species=\n|otherspecies=[[Human/Legends|Humans]]\n|socialgroup=\n|language=\n|government=\n|population=\n|demonym=\n|cities=\n|imports=\n|exports=\n|affiliation=[[Kathol Republic]]\n}}\n'''Jangelle''' was a [[Planet/Legends|planet]] in the [[Kathol sector/Legends|Kathol sector]]. A temperate world of sandy lowlands, it was crossed with many interlinking rivers, streams and deltas, although it had few large bodies of [[Water/Legends|water]].\n\nThe planet was settled by refugees fleeing the presence of the [[Galactic Empire/Legends|Galactic Empire]] in the Kathol sector. It was a low-tech, but largely self-sufficient colony, requiring only a few supply runs a year to [[Gandle Ott]] or [[Pembric II]]. These mostly included replacement parts for the three orbital weather satellites, power generators and the few dozen [[Droid/Legends|droids]] on the planet.\n\nJangelle had a mutual defense pact with the [[Kathol Republic]], with the Republic's [[Corvette/Legends|corvettes]] supplementing the colony's two capital ships. The colony was also defended by two [[Ion cannon/Legends|ion cannons]] positioned close to the settlement for orbital defense. Jangelle's isolation meant it was behind on important news and knew little about the [[New Republic/Legends|New Republic]]. Word of the [[Galactic Emperor/Legends|Emperor's]] death had reached them, but was presumed to be due to internal power struggles within the Empire, rather than the revolutionary movement. The colonists were also slow in receiving word of [[Moff/Legends|Moff]] [[Kentor Sarne]]'s retreat.\n\n==Appearances==\n*''[[Vision of the Future]]'' {{Ab|Vision of the Future (unabridged audiobook)}} {{Mo}}\n\n==Sources==\n*<!-- 1996-01-15 -->''[[The Kathol Outback]]''\n*<!-- 2008-12-09 -->''[[The Complete Star Wars Encyclopedia]]''\n\n{{Interlang\n|fi=Jangelle\n}}\n\n[[Category:Kathol Outback locations]]\n[[Category:Planets in the Outer Rim Territories]]\n[[Category:Terrestrial planets]]",
  "length": 2509,
  "lastmod": "2026-02-22T17:44:08Z",
  "priority": 1.0
}