{
  "url": "https://starwars.fandom.com/wiki/Thaffal",
  "title": "Thaffal",
  "pageid": 81021,
  "content": "{{Top|leg}}\n{{Character\n|type=\n|image=\n|name=Thaffal\n|homeworld=[[Haruun Kal/Legends|Haruun Kal]]\n|birth=\n|death=[[22 BBY/Legends|22 BBY]], Haruun Kal\n|species=[[Human/Legends|Human]] ([[Korun/Legends|Korun]])\n|gender=[[Gender/Legends|Male]]\n|pronouns=new\n|height=\n|mass=\n|hair=\n|feathers=\n|eyes=\n|skin=\n|cyber=\n|families=new\n|parents=new\n|partners=new\n|siblings=new\n|children=new\n|affiliation=[[Upland Liberation Front]]\n|masters=\n|apprentices=\n}}\n'''Thaffal''' was a [[Korun/Legends|Korun]] [[Gender/Legends|male]] [[Akk Guard]] from [[Haruun Kal/Legends|Haruun Kal]] during the [[Summertime War]].\n\n{{Char-stub}}\n\n==Biography==\nThaffal tried to oppose [[Jedi Master/Legends|Jedi Master]] [[Mace Windu/Legends|Mace Windu]] when he tried to free the [[Balawai]] prisoners from the Korunnai, causing Windu to break his nose.\n\nNear the end of the [[Summertime War]] in [[22 BBY/Legends|22 BBY]], he, the other Akk guards and [[Kar Vastor]] faced off against Windu, [[Nick Rostu]] and [[Galactic Republic/Legends|Galactic Republic]] forces. During [[Battle of Pelek Baw]] Thaffal slaughtered many [[Clone trooper/Legends|clone troopers]] with his [[vibroshield]]s. At the end, Rostu shot him at the knee, making him fall down, over a moribund trooper, who finally used his last effort to kill Thaffal with his [[DC-15s side arm blaster|DC-15s]] pistol.\n\n==Appearances==\n*[[Shatterpoint (novel)|''Shatterpoint'']] {{Ab|Shatterpoint (unabridged audiobook)}} {{1st|in book}}\n\n{{Interlang\n|de=Thaffal\n}}\n\n[[Category:Korunnai]]\n[[Category:Males]]\n[[Category:Resistance fighters]]",
  "length": 1572,
  "lastmod": "2025-11-16T04:33:16Z",
  "priority": 1.0
}