{
  "url": "https://starwars.fandom.com/wiki/Bha%27lir",
  "title": "Bha'lir",
  "pageid": 87367,
  "content": "{{Top|leg}}\n{{Species\n|image=[[File:Bhalir.jpg]]\n|name=Bha'lir\n|designation=\n|class=\n|subspecies=\n|races=\n|height=0.9&ndash;1.0 meters tall, 1.22 meters long\n|length=\n|wingspan=\n|mass=\n|skincolor=\n|haircolor=\n|feathers=\n|eyecolor=\n|distinctions=\n|lifespan=\n|origin=[[Iyred]]\n|habitat=\n|diet=\n|language=\n}}\n'''Bha'lir''' were jungle predators from the [[Planet/Legends|planet]] of [[Iyred]]. Though gentle when treated with caution, the bha'lir were quite territorial and would respond violently if threatened.<ref name=\"TBSOS\">''[[The Black Sands of Socorro]]''</ref>\n\n==Characteristics==\nThe bha'lir typically traveled in small pack families consisting of a [[Gender/Legends|male]], female, and six to seven cubs. Because the bha'lir [[Reproduction/Legends|mated]] for life, it was rare to see more than one male and female adult in a pack. When hunting, however, several bha'lir packs would often work together to exhaust their prey. Cubs and females ate before the males even though the males were bigger and stronger on average. This was the extent to which most bha'lir packs socialized.\n\n==History==\nDeforestation on [[Iyred]] drove the bha'lir so near extinction that they were officially declared extinct despite the few refuges that still existed. One such refuge on [[Duunir]] was funded by the [[Black Bha'lir]]. The loyalty of bha'lir to their mates made preservation of their [[Species/Legends|species]] even more difficult.\n\n==Sources==\n*<!-- 1997-06-XX -->''[[The Black Sands of Socorro]]''\n*<!-- 2008-12-09 -->{{CSWECite|II|126|Iyred}}\n\n==Notes and references==\n{{Reflist}}\n\n[[Category:Creatures of the Kibilini sector]]\n[[Category:Creatures of unspecified biology]]\n[[Category:Herd and pack creatures]]\n[[Category:Hunted creatures]]\n[[Category:Jungle and forest creatures]]\n[[Category:Predatory creatures]]\n[[Category:Species of undefined sentience]]",
  "length": 1867,
  "lastmod": "2025-11-16T04:33:17Z",
  "priority": 1.0
}