{
  "url": "https://starwars.fandom.com/wiki/Colonists",
  "title": "Colonists",
  "pageid": 89613,
  "content": "{{Top|leg}}\nThe '''Colonists''' were one of the two social factions of the [[Outbound Flight Colony]], the others being the [[Survivors (Outbound Flight)|Survivors]]. The Colonists were the ones who had been born after the ''[[Outbound Flight]]'' crashed in [[The Redoubt/Legends|the Redoubt]].\n\nThe [[Charter]] guaranteed that both factions were represented in the [[Managing Council]].\n\n{{Stub}}\n\n==Appearances==\n*''[[Survivor's Quest]]'' {{Ab|Survivor's Quest (unabridged audiobook)}}\n\n[[Category:Outbound Flight residents]]\n[[Category:Society and culture]]",
  "length": 560,
  "lastmod": "2025-11-16T04:33:17Z",
  "priority": 1.0
}