{
  "url": "https://starwars.fandom.com/wiki/Material_synthesis",
  "title": "Material synthesis",
  "pageid": 91087,
  "content": "{{Top|leg}}\n'''Material synthesis''' was a development of the ancient [[Gree (species)/Legends|Gree]] species and was a remarkable piece of technology. It allowed a reconfiguration of matter on a molecular level by changing its nuclear structure. This technology allowed the Gree to take simple basic elements such as [[Silicon/Legends|silicon]], [[Carbon/Legends|carbon]], and [[Hydrogen/Legends|hydrogen]] to create rarer and more valuable isotopes and elements. Masters within the Gree operator caste who specialized in material synthesis were called Synthesors.<ref name=\"The Gree Enclave\">{{JournalCite|8|The Gree Enclave}}</ref>\n\n==Sources==\n*<!-- 1995-11-XX -->{{JournalCite|8|The Gree Enclave|reprint=1}}\n\n==Notes and references==\n{{Reflist}}\n\n[[Category:Gree technology]]",
  "length": 780,
  "lastmod": "2026-02-09T21:04:39Z",
  "priority": 1.0
}