{
  "url": "https://starwars.fandom.com/wiki/Iain_Lowson",
  "title": "Iain Lowson",
  "pageid": 93423,
  "content": "{{Top|rwp}}\n{{Person\n|image=[[File:IainLowson.jpg]]\n|name=Iain Lowson\n|birth=\n|death=\n|listedpronouns=\n|nationality=\n|occupation=Author\n|companies=\n|website=\n}}\n'''Iain Lowson''' was the author of [[1998]]'s \"[[Down & Out on DB-24]]\" in the UK-published [[Polyhedron (UK)|''Polyhedron'']] [[Polyhedron (UK) 2|2]]&ndash;[[Polyhedron (UK) 3|3]] and an author of the ''[[The Official Star Wars Fact File]]'', published [[2002]] through [[2005]]. Before this, he worked on [[Titan Magazines|Titan's]] [[Star Wars: The Official Magazine|Official Star Wars Magazine]], as well as the original version of the UK Star Wars Fan Club. He was co-creator, editor and sole writer on the discontinued [[De Agostini]] follow-up to the Fact File, based on the Star Wars Miniatures game from [[Wizards of the Coast]]. That project, with floor plans from artist Andy J. Hepworth, was well received by fans in the few places it saw release, but never made it past issue four.\n\nIain later worked on the UK version of De Agostini's ''[[Star Wars: The Official Starships & Vehicles Collection]]''.\n\n{{Bio-stub}}\n\n==External links==\n*{{Blogspot|subdomain=embraagain|name=Embra, again.}}\n\n{{Interlang\n|tr=Iain Lowson\n}}\n\n[[Category:Reference work authors]]",
  "length": 1232,
  "lastmod": "2026-03-04T21:03:18Z",
  "priority": 1.0
}